gradio_box_promptable_image/__init__.py
gradio_box_promptable_image/box_promptable_image.py
gradio_box_promptable_image/box_promptable_image.pyi
gradio_box_promptable_image/templates/component/__vite-browser-external-2447137e.js
gradio_box_promptable_image/templates/component/index.js
gradio_box_promptable_image/templates/component/style.css
gradio_box_promptable_image/templates/component/wrapper-6f348d45-f837cf34.js
gradio_box_promptable_image/templates/example/index.js
gradio_box_promptable_image/templates/example/style.css
gradio_box_promptable_image-0.0.1.dist-info/METADATA
gradio_box_promptable_image-0.0.1.dist-info/WHEEL
gradio_box_promptable_image-0.0.1.dist-info/RECORD
